{"GameDate":"2025-06-19T00:00:00-05:00","StartTime":"2025-06-19T17:50:48.5613446-05:00","EndTime":"2025-06-19T19:45:26.914631-05:00","AwayTeamHitting":[{"PlayerDisplay":"Lehman, B","PlayerName":"B. Lehman","Player":{"Position":{"IsPitcher":true,"PositionNumber":10,"PositionString":"EH","LongPositionString":"Extra Hitter","PositionText":"","DisplayString":"DH / P / C / _1B / IF / OF / EH"},"Id":0,"Number":2,"DisplayNumber":"2","FirstName":"Brian","LastName":"Lehman","DisplayName":"Lehman"},"G":0,"Doubles":0,"Triples":0,"HR":0,"AB":4,"Runs":1,"H":2,"BB":0,"K":0,"SB":1,"CS":0,"RBI":0,"HBP":0,"SAC":0,"SF":0,"BaFormatted":".500","BA":0.5,"SlgFormatted":".500","SLG":0.5,"ObpFormatted":".500","OBP":0.5,"OpsFormatted":"1.000","OPS":1.0},{"PlayerDisplay":"Kruse, A","PlayerName":"A. Kruse","Player":{"Position":{"IsPitcher":false,"PositionNumber":5,"PositionString":"3B","LongPositionString":"Third Base","PositionText":"third","DisplayString":"_3B"},"Id":0,"Number":11,"DisplayNumber":"11","FirstName":"Arron","LastName":"Kruse","DisplayName":"Kruse"},"G":0,"Doubles":0,"Triples":0,"HR":0,"AB":4,"Runs":0,"H":1,"BB":0,"K":0,"SB":0,"CS":0,"RBI":0,"HBP":0,"SAC":0,"SF":0,"BaFormatted":".250","BA":0.25,"SlgFormatted":".250","SLG":0.25,"ObpFormatted":".250","OBP":0.25,"OpsFormatted":".500","OPS":0.50},{"PlayerDisplay":"Riggenbach, T","PlayerName":"T. Riggenbach","Player":{"Position":{"IsPitcher":true,"PositionNumber":10,"PositionString":"EH","LongPositionString":"Extra Hitter","PositionText":"","DisplayString":"DH / P / C / _1B / IF / OF / EH"},"Id":0,"Number":8,"DisplayNumber":"8","FirstName":"Tim","LastName":"Riggenbach","DisplayName":"Riggenbach"},"G":0,"Doubles":0,"Triples":0,"HR":0,"AB":4,"Runs":0,"H":1,"BB":0,"K":2,"SB":0,"CS":0,"RBI":0,"HBP":0,"SAC":0,"SF":0,"BaFormatted":".250","BA":0.25,"SlgFormatted":".250","SLG":0.25,"ObpFormatted":".250","OBP":0.25,"OpsFormatted":".500","OPS":0.50},{"PlayerDisplay":"Jessee, B","PlayerName":"B. Jessee","Player":{"Position":{"IsPitcher":false,"PositionNumber":7,"PositionString":"LF","LongPositionString":"Left Field","PositionText":"left","DisplayString":"LF"},"Id":0,"Number":3,"DisplayNumber":"3","FirstName":"Brandon","LastName":"Jessee","DisplayName":"Jessee"},"G":0,"Doubles":0,"Triples":0,"HR":0,"AB":4,"Runs":0,"H":1,"BB":0,"K":0,"SB":0,"CS":0,"RBI":1,"HBP":0,"SAC":0,"SF":0,"BaFormatted":".250","BA":0.25,"SlgFormatted":".250","SLG":0.25,"ObpFormatted":".250","OBP":0.25,"OpsFormatted":".500","OPS":0.50},{"PlayerDisplay":"Cantor, J","PlayerName":"J. Cantor","Player":{"Position":{"IsPitcher":false,"PositionNumber":3,"PositionString":"1B","LongPositionString":"First Base","PositionText":"first","DisplayString":"_1B"},"Id":0,"Number":34,"DisplayNumber":"34","FirstName":"Jules","LastName":"Cantor","DisplayName":"Cantor"},"G":0,"Doubles":0,"Triples":0,"HR":0,"AB":3,"Runs":0,"H":0,"BB":0,"K":0,"SB":0,"CS":0,"RBI":0,"HBP":0,"SAC":0,"SF":0,"BaFormatted":".000","BA":0,"SlgFormatted":".000","SLG":0,"ObpFormatted":".000","OBP":0,"OpsFormatted":".000","OPS":0},{"PlayerDisplay":"Bandi, J","PlayerName":"J. Bandi","Player":{"Position":{"IsPitcher":false,"PositionNumber":8,"PositionString":"CF","LongPositionString":"Center Field","PositionText":"center","DisplayString":"CF"},"Id":0,"Number":27,"DisplayNumber":"27","FirstName":"Japheth","LastName":"Bandi","DisplayName":"Bandi"},"G":0,"Doubles":0,"Triples":0,"HR":0,"AB":2,"Runs":0,"H":0,"BB":1,"K":1,"SB":0,"CS":0,"RBI":0,"HBP":0,"SAC":0,"SF":0,"BaFormatted":".000","BA":0,"SlgFormatted":".000","SLG":0,"ObpFormatted":".333","OBP":0.333,"OpsFormatted":".333","OPS":0.333},{"PlayerDisplay":"Zelenka, P","PlayerName":"P. Zelenka","Player":{"Position":{"IsPitcher":false,"PositionNumber":4,"PositionString":"2B","LongPositionString":"Second Base","PositionText":"second","DisplayString":"_2B"},"Id":0,"Number":21,"DisplayNumber":"21","FirstName":"Phil","LastName":"Zelenka","DisplayName":"Zelenka"},"G":0,"Doubles":0,"Triples":0,"HR":0,"AB":3,"Runs":1,"H":0,"BB":0,"K":2,"SB":1,"CS":0,"RBI":0,"HBP":0,"SAC":0,"SF":0,"BaFormatted":".000","BA":0,"SlgFormatted":".000","SLG":0,"ObpFormatted":".000","OBP":0,"OpsFormatted":".000","OPS":0},{"PlayerDisplay":"Player, U","PlayerName":"U. Player","Player":{"Position":{"IsPitcher":false,"PositionNumber":6,"PositionString":"SS","LongPositionString":"Shortstop","PositionText":"shortstop","DisplayString":"SS"},"Id":0,"Number":13,"DisplayNumber":"13","FirstName":"Unknown","LastName":"Player","DisplayName":"Player #13"},"G":0,"Doubles":0,"Triples":0,"HR":0,"AB":2,"Runs":0,"H":1,"BB":1,"K":1,"SB":0,"CS":0,"RBI":1,"HBP":0,"SAC":0,"SF":0,"BaFormatted":".500","BA":0.5,"SlgFormatted":".500","SLG":0.5,"ObpFormatted":".667","OBP":0.667,"OpsFormatted":"1.167","OPS":1.167},{"PlayerDisplay":"Trivett, Z","PlayerName":"Z. Trivett","Player":{"Position":{"IsPitcher":false,"PositionNumber":2,"PositionString":"C","LongPositionString":"Catcher","PositionText":"catcher","DisplayString":"C"},"Id":0,"Number":25,"DisplayNumber":"25","FirstName":"Zack","LastName":"Trivett","DisplayName":"Trivett"},"G":0,"Doubles":0,"Triples":0,"HR":0,"AB":2,"Runs":0,"H":0,"BB":1,"K":0,"SB":0,"CS":0,"RBI":0,"HBP":0,"SAC":0,"SF":0,"BaFormatted":".000","BA":0,"SlgFormatted":".000","SLG":0,"ObpFormatted":".333","OBP":0.333,"OpsFormatted":".333","OPS":0.333}],"HomeTeamHitting":[{"PlayerDisplay":"Eiden, T","PlayerName":"T. Eiden","Player":{"Position":{"IsPitcher":true,"PositionNumber":1,"PositionString":"P","LongPositionString":"Pitcher","PositionText":"pitcher","DisplayString":"P"},"Id":0,"Number":23,"DisplayNumber":"23","FirstName":"Tim","LastName":"Eiden","DisplayName":"Eiden"},"G":0,"Doubles":0,"Triples":0,"HR":0,"AB":3,"Runs":1,"H":2,"BB":1,"K":0,"SB":0,"CS":0,"RBI":1,"HBP":0,"SAC":0,"SF":0,"BaFormatted":".667","BA":0.667,"SlgFormatted":".667","SLG":0.667,"ObpFormatted":".750","OBP":0.75,"OpsFormatted":"1.417","OPS":1.417},{"PlayerDisplay":"Van Kooten, T","PlayerName":"T. Van Kooten","Player":{"Position":{"IsPitcher":false,"PositionNumber":6,"PositionString":"SS","LongPositionString":"Shortstop","PositionText":"shortstop","DisplayString":"SS"},"Id":0,"Number":27,"DisplayNumber":"27","FirstName":"Tom","LastName":"Van Kooten","DisplayName":"Van Kooten"},"G":0,"Doubles":0,"Triples":0,"HR":0,"AB":3,"Runs":0,"H":0,"BB":0,"K":2,"SB":0,"CS":0,"RBI":0,"HBP":0,"SAC":0,"SF":0,"BaFormatted":".000","BA":0,"SlgFormatted":".000","SLG":0,"ObpFormatted":".000","OBP":0,"OpsFormatted":".000","OPS":0},{"PlayerDisplay":"Anderson, S","PlayerName":"S. Anderson","Player":{"Position":{"IsPitcher":false,"PositionNumber":3,"PositionString":"1B","LongPositionString":"First Base","PositionText":"first","DisplayString":"_1B"},"Id":0,"Number":28,"DisplayNumber":"28","FirstName":"Steve","LastName":"Anderson","DisplayName":"Anderson"},"G":0,"Doubles":2,"Triples":0,"HR":0,"AB":3,"Runs":0,"H":2,"BB":0,"K":0,"SB":0,"CS":0,"RBI":2,"HBP":0,"SAC":0,"SF":0,"BaFormatted":".667","BA":0.667,"SlgFormatted":"1.333","SLG":1.333,"ObpFormatted":".667","OBP":0.667,"OpsFormatted":"2.000","OPS":2.000},{"PlayerDisplay":"Russman, E","PlayerName":"E. Russman","Player":{"Position":{"IsPitcher":true,"PositionNumber":10,"PositionString":"EH","LongPositionString":"Extra Hitter","PositionText":"","DisplayString":"DH / P / C / _1B / IF / OF / EH"},"Id":0,"Number":44,"DisplayNumber":"44","FirstName":"Eric","LastName":"Russman","DisplayName":"Russman"},"G":0,"Doubles":0,"Triples":0,"HR":0,"AB":2,"Runs":0,"H":0,"BB":1,"K":0,"SB":0,"CS":0,"RBI":0,"HBP":0,"SAC":0,"SF":0,"BaFormatted":".000","BA":0,"SlgFormatted":".000","SLG":0,"ObpFormatted":".333","OBP":0.333,"OpsFormatted":".333","OPS":0.333},{"PlayerDisplay":"Millner, J","PlayerName":"J. Millner","Player":{"Position":{"IsPitcher":false,"PositionNumber":5,"PositionString":"3B","LongPositionString":"Third Base","PositionText":"third","DisplayString":"_3B"},"Id":0,"Number":24,"DisplayNumber":"24","FirstName":"Justin","LastName":"Millner","DisplayName":"Millner"},"G":0,"Doubles":0,"Triples":0,"HR":0,"AB":2,"Runs":1,"H":1,"BB":1,"K":1,"SB":0,"CS":0,"RBI":0,"HBP":0,"SAC":0,"SF":0,"BaFormatted":".500","BA":0.5,"SlgFormatted":".500","SLG":0.5,"ObpFormatted":".667","OBP":0.667,"OpsFormatted":"1.167","OPS":1.167},{"PlayerDisplay":"DeSoto, I","PlayerName":"I. DeSoto","Player":{"Position":{"IsPitcher":false,"PositionNumber":4,"PositionString":"2B","LongPositionString":"Second Base","PositionText":"second","DisplayString":"_2B"},"Id":0,"Number":9,"DisplayNumber":"9","FirstName":"Ian","LastName":"DeSoto","DisplayName":"DeSoto"},"G":0,"Doubles":1,"Triples":0,"HR":0,"AB":2,"Runs":1,"H":1,"BB":0,"K":0,"SB":0,"CS":0,"RBI":0,"HBP":0,"SAC":0,"SF":0,"BaFormatted":".500","BA":0.5,"SlgFormatted":"1.000","SLG":1,"ObpFormatted":".500","OBP":0.5,"OpsFormatted":"1.500","OPS":1.5},{"PlayerDisplay":"Lui, C","PlayerName":"C. Lui","Player":{"Position":{"IsPitcher":false,"PositionNumber":9,"PositionString":"RF","LongPositionString":"Right Field","PositionText":"right","DisplayString":"RF"},"Id":0,"Number":73,"DisplayNumber":"73","FirstName":"Cyrus","LastName":"Lui","DisplayName":"Lui"},"G":0,"Doubles":0,"Triples":0,"HR":0,"AB":3,"Runs":1,"H":1,"BB":0,"K":2,"SB":0,"CS":0,"RBI":1,"HBP":0,"SAC":0,"SF":0,"BaFormatted":".333","BA":0.333,"SlgFormatted":".333","SLG":0.333,"ObpFormatted":".333","OBP":0.333,"OpsFormatted":".666","OPS":0.666},{"PlayerDisplay":"McElhaney, B","PlayerName":"B. McElhaney","Player":{"Position":{"IsPitcher":false,"PositionNumber":8,"PositionString":"CF","LongPositionString":"Center Field","PositionText":"center","DisplayString":"CF"},"Id":0,"Number":12,"DisplayNumber":"12","FirstName":"Brendan","LastName":"McElhaney","DisplayName":"McElhaney"},"G":0,"Doubles":0,"Triples":0,"HR":0,"AB":1,"Runs":2,"H":0,"BB":1,"K":0,"SB":1,"CS":0,"RBI":1,"HBP":1,"SAC":0,"SF":0,"BaFormatted":".000","BA":0,"SlgFormatted":".000","SLG":0,"ObpFormatted":".667","OBP":0.667,"OpsFormatted":".667","OPS":0.667},{"PlayerDisplay":"Jacobs, B","PlayerName":"B. Jacobs","Player":{"Position":{"IsPitcher":false,"PositionNumber":2,"PositionString":"C","LongPositionString":"Catcher","PositionText":"catcher","DisplayString":"C"},"Id":0,"Number":30,"DisplayNumber":"30","FirstName":"Ben","LastName":"Jacobs","DisplayName":"Jacobs"},"G":0,"Doubles":0,"Triples":0,"HR":0,"AB":2,"Runs":0,"H":0,"BB":0,"K":0,"SB":0,"CS":0,"RBI":1,"HBP":0,"SAC":0,"SF":1,"BaFormatted":".000","BA":0,"SlgFormatted":".000","SLG":0,"ObpFormatted":".000","OBP":0,"OpsFormatted":".000","OPS":0},{"PlayerDisplay":"Wojcik, A","PlayerName":"A. Wojcik","Player":{"Position":{"IsPitcher":false,"PositionNumber":7,"PositionString":"LF","LongPositionString":"Left Field","PositionText":"left","DisplayString":"LF"},"Id":0,"Number":26,"DisplayNumber":"26","FirstName":"Andy","LastName":"Wojcik","DisplayName":"Wojcik"},"G":0,"Doubles":1,"Triples":0,"HR":0,"AB":2,"Runs":1,"H":1,"BB":0,"K":0,"SB":0,"CS":0,"RBI":2,"HBP":0,"SAC":0,"SF":0,"BaFormatted":".500","BA":0.5,"SlgFormatted":"1.000","SLG":1,"ObpFormatted":".500","OBP":0.5,"OpsFormatted":"1.500","OPS":1.5},{"PlayerDisplay":"Rattin, P","PlayerName":"P. Rattin","Player":{"Position":{"IsPitcher":false,"PositionNumber":4,"PositionString":"2B","LongPositionString":"Second Base","PositionText":"second","DisplayString":"_2B"},"Id":0,"Number":29,"DisplayNumber":"29","FirstName":"Peter","LastName":"Rattin","DisplayName":"Rattin"},"G":0,"Doubles":0,"Triples":0,"HR":0,"AB":1,"Runs":0,"H":0,"BB":0,"K":0,"SB":0,"CS":0,"RBI":0,"HBP":0,"SAC":0,"SF":0,"BaFormatted":".000","BA":0,"SlgFormatted":".000","SLG":0,"ObpFormatted":".000","OBP":0,"OpsFormatted":".000","OPS":0},{"PlayerDisplay":"Guckenberger, J","PlayerName":"J. Guckenberger","Player":{"Position":{"IsPitcher":false,"PositionNumber":7,"PositionString":"LF","LongPositionString":"Left Field","PositionText":"left","DisplayString":"LF"},"Id":0,"Number":71,"DisplayNumber":"71","FirstName":"Jimmy","LastName":"Guckenberger","DisplayName":"Guckenberger"},"G":0,"Doubles":0,"Triples":0,"HR":0,"AB":0,"Runs":0,"H":0,"BB":0,"K":0,"SB":1,"CS":1,"RBI":0,"HBP":1,"SAC":0,"SF":0,"BaFormatted":".000","BA":null,"SlgFormatted":".000","SLG":null,"ObpFormatted":"1.000","OBP":1,"OpsFormatted":"1.000","OPS":1}],"AwayTeamPitching":[{"PitcherDisplay":"A. Conway (L)","PlayerName":"A. Conway","Player":{"Position":{"IsPitcher":true,"PositionNumber":1,"PositionString":"P","LongPositionString":"Pitcher","PositionText":"pitcher","DisplayString":"P"},"Id":0,"Number":23,"DisplayNumber":"23","FirstName":"Atticus","LastName":"Conway","DisplayName":"Conway"},"Decision":2,"DecisionDiplay":"L","GS":1,"H":6,"HR":0,"BB":0,"K":1,"HB":1,"BF":14,"R":6,"ER":5,"Outs":6,"IP":"2.0","CG":0,"EraFormatted":"17.50","ERA":17.5,"WhipFormatted":"3.00","WHIP":3,"K9":3.5,"BB9":0,"Pitches":0,"Balls":0,"Strikes":0,"GroundOuts":1,"FlyOuts":3},{"PitcherDisplay":"L. Peterson ","PlayerName":"L. Peterson","Player":{"Position":{"IsPitcher":true,"PositionNumber":1,"PositionString":"P","LongPositionString":"Pitcher","PositionText":"pitcher","DisplayString":"P"},"Id":0,"Number":45,"DisplayNumber":"45","FirstName":"Lucas","LastName":"Peterson","DisplayName":"Peterson"},"Decision":0,"DecisionDiplay":"","GS":0,"H":1,"HR":0,"BB":2,"K":2,"HB":0,"BF":8,"R":1,"ER":1,"Outs":6,"IP":"2.0","CG":0,"EraFormatted":"3.50","ERA":3.5,"WhipFormatted":"1.50","WHIP":1.5,"K9":7,"BB9":7,"Pitches":0,"Balls":0,"Strikes":0,"GroundOuts":2,"FlyOuts":1},{"PitcherDisplay":"B. Lehman ","PlayerName":"B. Lehman","Player":{"Position":{"IsPitcher":true,"PositionNumber":1,"PositionString":"P","LongPositionString":"Pitcher","PositionText":"pitcher","DisplayString":"P"},"Id":0,"Number":2,"DisplayNumber":"2","FirstName":"Brian","LastName":"Lehman","DisplayName":"Lehman"},"Decision":0,"DecisionDiplay":"","GS":0,"H":1,"HR":0,"BB":2,"K":2,"HB":1,"BF":12,"R":0,"ER":0,"Outs":6,"IP":"2.0","CG":0,"EraFormatted":".00","ERA":0,"WhipFormatted":"1.50","WHIP":1.5,"K9":7,"BB9":7,"Pitches":0,"Balls":0,"Strikes":0,"GroundOuts":2,"FlyOuts":0}],"HomeTeamPitching":[{"PitcherDisplay":"T. Eiden (W)","PlayerName":"T. Eiden","Player":{"Position":{"IsPitcher":true,"PositionNumber":1,"PositionString":"P","LongPositionString":"Pitcher","PositionText":"pitcher","DisplayString":"P"},"Id":0,"Number":23,"DisplayNumber":"23","FirstName":"Tim","LastName":"Eiden","DisplayName":"Eiden"},"Decision":1,"DecisionDiplay":"W","GS":1,"H":6,"HR":0,"BB":1,"K":3,"HB":0,"BF":22,"R":2,"ER":1,"Outs":15,"IP":"5.0","CG":0,"EraFormatted":"1.40","ERA":1.4,"WhipFormatted":"1.40","WHIP":1.4,"K9":4.2,"BB9":1.4,"Pitches":0,"Balls":0,"Strikes":0,"GroundOuts":3,"FlyOuts":8},{"PitcherDisplay":"J. Guckenberger ","PlayerName":"J. Guckenberger","Player":{"Position":{"IsPitcher":true,"PositionNumber":1,"PositionString":"P","LongPositionString":"Pitcher","PositionText":"pitcher","DisplayString":"P"},"Id":0,"Number":71,"DisplayNumber":"71","FirstName":"Jimmy","LastName":"Guckenberger","DisplayName":"Guckenberger"},"Decision":0,"DecisionDiplay":"","GS":0,"H":0,"HR":0,"BB":2,"K":3,"HB":0,"BF":9,"R":0,"ER":0,"Outs":6,"IP":"2.0","CG":0,"EraFormatted":".00","ERA":0,"WhipFormatted":"1.00","WHIP":1,"K9":10.5,"BB9":7,"Pitches":0,"Balls":0,"Strikes":0,"GroundOuts":3,"FlyOuts":0}],"WinningPitcher":{"Position":null,"Id":0,"Number":23,"DisplayNumber":"23","FirstName":"Tim","LastName":"Eiden","DisplayName":"Eiden"},"LosingPitcher":{"Position":null,"Id":0,"Number":23,"DisplayNumber":"23","FirstName":"Atticus","LastName":"Conway","DisplayName":"Conway"},"current_ab":{"balls":0,"strikes":0,"outs":1,"pitches":[],"inning_number":7,"inning_half":"Top","on_first":null,"on_second":null,"on_third":null},"defense":{"1":"Guckenberger","6":"Van Kooten","3":"Anderson","10":"Russman","5":"Millner","4":"Rattin","9":"Lui","8":"McElhaney","2":"Jacobs","7":"Guckenberger"},"home_score":7,"away_score":2,"home_hits":8,"away_hits":6,"home_errors":2,"away_errors":2,"ScoringPlays":[{"HomeScore":0,"AwayScore":1,"InningNumber":1,"Team":"Hounds","Play":"Jessee singled.  Lehman scored.  "},{"HomeScore":0,"AwayScore":2,"InningNumber":2,"Team":"Hounds","Play":"Player singled.  Zelenka scored.  "},{"HomeScore":1,"AwayScore":2,"InningNumber":2,"Team":"Electrons","Play":"McElhaney hit by pitch.  Millner scored.  "},{"HomeScore":2,"AwayScore":2,"InningNumber":2,"Team":"Electrons","Play":"Jacobs hit a sacrifice fly to right.  DeSoto scored.  "},{"HomeScore":4,"AwayScore":2,"InningNumber":2,"Team":"Electrons","Play":"Wojcik doubled to center.  Lui and McElhaney scored.  "},{"HomeScore":6,"AwayScore":2,"InningNumber":2,"Team":"Electrons","Play":"Anderson doubled to deep center.  Wojcik and Eiden scored.  "},{"HomeScore":7,"AwayScore":2,"InningNumber":4,"Team":"Electrons","Play":"Eiden singled.  McElhaney scored.  "}],"GameSummary":[{"Description":"Top of 1","Summary":"1 Run, 2 Hits, 0 Errors, 1 Left","Events":[{"EventText":"Lehman singled.  ","ScoringPlay":false},{"EventText":"Kruse flied out to shortstop.  ","ScoringPlay":false},{"EventText":"Lehman stole second.  Riggenbach struck out.  ","ScoringPlay":false},{"EventText":"Jessee singled.  Lehman scored.  ","ScoringPlay":true},{"EventText":"Cantor flied out to right.  ","ScoringPlay":false}]},{"Description":"Bottom of 1","Summary":"0 Runs, 1 Hit, 0 Errors, 1 Left","Events":[{"EventText":"Eiden singled to center.  ","ScoringPlay":false},{"EventText":"Van Kooten reached on fielder\u0027s choice to third.  Eiden out at second.  ","ScoringPlay":false},{"EventText":"Anderson flied out to right.  ","ScoringPlay":false},{"EventText":"Russman flied out to left.  ","ScoringPlay":false}]},{"Description":"Top of 2","Summary":"1 Run, 3 Hits, 1 Error, 2 Left","Events":[{"EventText":"Bandi struck out.  ","ScoringPlay":false},{"EventText":"Zelenka reached on an error to shortstop.  ","ScoringPlay":false},{"EventText":"Zelenka stole second.  Player singled.  Zelenka scored.  ","ScoringPlay":true},{"EventText":"Trivett flied out to first.  ","ScoringPlay":false},{"EventText":"Lehman singled.  ","ScoringPlay":false},{"EventText":"Kruse singled.  Player #13 out at Home.  ","ScoringPlay":false}]},{"Description":"Bottom of 2","Summary":"6 Runs, 5 Hits, 1 Error, 1 Left","Events":[{"EventText":"Millner singled.  ","ScoringPlay":false},{"EventText":"DeSoto doubled to deep center.  ","ScoringPlay":false},{"EventText":"Lui singled.  ","ScoringPlay":false},{"EventText":"McElhaney hit by pitch.  Millner scored.  ","ScoringPlay":true},{"EventText":"Jacobs hit a sacrifice fly to right.  DeSoto scored.  ","ScoringPlay":true},{"EventText":"McElhaney stole second.  Wojcik doubled to center.  Lui and McElhaney scored.  ","ScoringPlay":true},{"EventText":"Eiden reached on an error to third.  ","ScoringPlay":false},{"EventText":"Van Kooten struck out.  ","ScoringPlay":false},{"EventText":"Anderson doubled to deep center.  Wojcik and Eiden scored.  ","ScoringPlay":true},{"EventText":"Russman flied out to right.  ","ScoringPlay":false}]},{"Description":"Top of 3","Summary":"0 Runs, 1 Hit, 0 Errors, 1 Left","Events":[{"EventText":"Riggenbach singled to right.  ","ScoringPlay":false},{"EventText":"Jessee reached on fielder\u0027s choice to second.  Riggenbach out at second.  ","ScoringPlay":false},{"EventText":"Cantor flied out to second.  ","ScoringPlay":false},{"EventText":"Bandi flied out to center.  ","ScoringPlay":false}]},{"Description":"Bottom of 3","Summary":"0 Runs, 0 Hits, 0 Errors, 0 Left","Events":[{"EventText":"L. Peterson relieved A. Conway.  Millner walked.  ","ScoringPlay":false},{"EventText":"DeSoto lined into a double play to shortstop.  Millner out at first.  ","ScoringPlay":false},{"EventText":"Lui struck out.  ","ScoringPlay":false}]},{"Description":"Top of 4","Summary":"0 Runs, 0 Hits, 0 Errors, 1 Left","Events":[{"EventText":"Zelenka struck out.  ","ScoringPlay":false},{"EventText":"Player #13 walked.  ","ScoringPlay":false},{"EventText":"Trivett flied out to shortstop.  ","ScoringPlay":false},{"EventText":"Lehman grounded out to second.  ","ScoringPlay":false}]},{"Description":"Bottom of 4","Summary":"1 Run, 1 Hit, 0 Errors, 1 Left","Events":[{"EventText":"McElhaney walked.  ","ScoringPlay":false},{"EventText":"Jacobs grounded out to second.  ","ScoringPlay":false},{"EventText":"Wojcik grounded out to third.  ","ScoringPlay":false},{"EventText":"Eiden singled.  McElhaney scored.  ","ScoringPlay":true},{"EventText":"Van Kooten struck out.  ","ScoringPlay":false}]},{"Description":"Top of 5","Summary":"0 Runs, 0 Hits, 0 Errors, 0 Left","Events":[{"EventText":"Kruse flied out to center.  ","ScoringPlay":false},{"EventText":"Riggenbach grounded out to first.  ","ScoringPlay":false},{"EventText":"Jessee flied out to first.  ","ScoringPlay":false}]},{"Description":"Bottom of 5","Summary":"0 Runs, 1 Hit, 0 Errors, 2 Left","Events":[{"EventText":"B. Lehman relieved L. Peterson.  Anderson doubled to center.  ","ScoringPlay":false},{"EventText":"Russman walked.  ","ScoringPlay":false},{"EventText":"Millner struck out.  ","ScoringPlay":false},{"EventText":"Rattin batted for DeSoto.  ","ScoringPlay":false},{"EventText":"Rattin reached on fielder\u0027s choice to second.  Russman out at second.  ","ScoringPlay":false},{"EventText":"Lui struck out.  ","ScoringPlay":false}]},{"Description":"Top of 6","Summary":"0 Runs, 0 Hits, 1 Error, 3 Left","Events":[{"EventText":"J. Guckenberger relieved T. Eiden.  Cantor reached on an error to first.  ","ScoringPlay":false},{"EventText":"Bandi walked.  ","ScoringPlay":false},{"EventText":"Zelenka struck out.  ","ScoringPlay":false},{"EventText":"Player #13 struck out.  ","ScoringPlay":false},{"EventText":"Trivett walked.  ","ScoringPlay":false},{"EventText":"Lehman reached on fielder\u0027s choice to shortstop.  Trivett out at second.  ","ScoringPlay":false}]},{"Description":"Bottom of 6","Summary":"0 Runs, 0 Hits, 1 Error, 1 Left","Events":[{"EventText":"McElhaney reached on an error to shortstop.  ","ScoringPlay":false},{"EventText":"Jacobs hit into a double play to right.  McElhaney out at second.  ","ScoringPlay":false},{"EventText":"Guckenberger batted for Wojcik.  ","ScoringPlay":false},{"EventText":"Guckenberger hit by pitch.  ","ScoringPlay":false},{"EventText":"Guckenberger stole second.  Eiden walked.  ","ScoringPlay":false},{"EventText":"Van Kooten batting in the Bottom of 6.  Guckenberger caught stealing.  ","ScoringPlay":false}]},{"Description":"Top of 7","Summary":"0 Runs, 0 Hits, 0 Errors, 0 Left","Events":[{"EventText":"Kruse grounded out to second.  ","ScoringPlay":false},{"EventText":"Riggenbach struck out.  ","ScoringPlay":false},{"EventText":"Jessee grounded out to second.  ","ScoringPlay":false}]}],"GameLineScore":{"HomeLine":{"Name":"Electrons","InningLines":[{"Runs":0,"Hits":0,"Errors":1,"Number":6},{"Runs":0,"Hits":1,"Errors":0,"Number":5},{"Runs":1,"Hits":1,"Errors":0,"Number":4},{"Runs":0,"Hits":0,"Errors":0,"Number":3},{"Runs":6,"Hits":5,"Errors":1,"Number":2},{"Runs":0,"Hits":1,"Errors":0,"Number":1}]},"AwayLine":{"Name":"Hounds","InningLines":[{"Runs":0,"Hits":0,"Errors":0,"Number":7},{"Runs":0,"Hits":0,"Errors":1,"Number":6},{"Runs":0,"Hits":0,"Errors":0,"Number":5},{"Runs":0,"Hits":0,"Errors":0,"Number":4},{"Runs":0,"Hits":1,"Errors":0,"Number":3},{"Runs":1,"Hits":3,"Errors":1,"Number":2},{"Runs":1,"Hits":2,"Errors":0,"Number":1}]}},"home_risp":{"abs":11,"hits":4},"away_risp":{"abs":7,"hits":3}}