{"GameDate":"2022-06-04T00:00:00-05:00","StartTime":"2022-06-04T12:30:19.3128889-05:00","EndTime":"2022-06-04T14:32:21.7036527-05:00","AwayTeamHitting":[{"PlayerDisplay":"Player, U","PlayerName":"U. Player","Player":{"Position":{"IsPitcher":false,"PositionNumber":6,"PositionString":"SS","LongPositionString":"Shortstop","PositionText":"shortstop","DisplayString":"SS"},"Id":0,"Number":0,"DisplayNumber":"0","FirstName":"Unknown","LastName":"Player","DisplayName":"Player #0"},"G":0,"Doubles":0,"Triples":0,"HR":0,"AB":2,"Runs":0,"H":0,"BB":0,"K":0,"SB":0,"CS":0,"RBI":0,"HBP":0,"SAC":0,"SF":0,"BaFormatted":".000","BA":0,"SlgFormatted":".000","SLG":0,"ObpFormatted":".000","OBP":0,"OpsFormatted":".000","OPS":0},{"PlayerDisplay":"Player, U","PlayerName":"U. Player","Player":{"Position":{"IsPitcher":false,"PositionNumber":4,"PositionString":"2B","LongPositionString":"Second Base","PositionText":"second","DisplayString":"_2B"},"Id":0,"Number":2,"DisplayNumber":"2","FirstName":"Unknown","LastName":"Player","DisplayName":"Player #2"},"G":0,"Doubles":0,"Triples":0,"HR":0,"AB":2,"Runs":0,"H":0,"BB":0,"K":0,"SB":0,"CS":0,"RBI":0,"HBP":0,"SAC":0,"SF":0,"BaFormatted":".000","BA":0,"SlgFormatted":".000","SLG":0,"ObpFormatted":".000","OBP":0,"OpsFormatted":".000","OPS":0},{"PlayerDisplay":"Player, U","PlayerName":"U. Player","Player":{"Position":{"IsPitcher":false,"PositionNumber":3,"PositionString":"1B","LongPositionString":"First Base","PositionText":"first","DisplayString":"_1B"},"Id":0,"Number":34,"DisplayNumber":"34","FirstName":"Unknown","LastName":"Player","DisplayName":"Player #34"},"G":0,"Doubles":0,"Triples":0,"HR":0,"AB":2,"Runs":0,"H":0,"BB":0,"K":1,"SB":0,"CS":0,"RBI":0,"HBP":0,"SAC":0,"SF":0,"BaFormatted":".000","BA":0,"SlgFormatted":".000","SLG":0,"ObpFormatted":".000","OBP":0,"OpsFormatted":".000","OPS":0},{"PlayerDisplay":"Player, U","PlayerName":"U. Player","Player":{"Position":{"IsPitcher":false,"PositionNumber":7,"PositionString":"LF","LongPositionString":"Left Field","PositionText":"left","DisplayString":"LF"},"Id":0,"Number":7,"DisplayNumber":"7","FirstName":"Unknown","LastName":"Player","DisplayName":"Player #7"},"G":0,"Doubles":0,"Triples":0,"HR":0,"AB":2,"Runs":0,"H":1,"BB":0,"K":0,"SB":0,"CS":0,"RBI":0,"HBP":0,"SAC":0,"SF":0,"BaFormatted":".500","BA":0.5,"SlgFormatted":".500","SLG":0.5,"ObpFormatted":".500","OBP":0.5,"OpsFormatted":"1.000","OPS":1.0},{"PlayerDisplay":"Player, U","PlayerName":"U. Player","Player":{"Position":{"IsPitcher":false,"PositionNumber":5,"PositionString":"3B","LongPositionString":"Third Base","PositionText":"third","DisplayString":"_3B"},"Id":0,"Number":99,"DisplayNumber":"99","FirstName":"Unknown","LastName":"Player","DisplayName":"Player #99"},"G":0,"Doubles":0,"Triples":0,"HR":0,"AB":2,"Runs":0,"H":0,"BB":0,"K":2,"SB":0,"CS":0,"RBI":0,"HBP":0,"SAC":0,"SF":0,"BaFormatted":".000","BA":0,"SlgFormatted":".000","SLG":0,"ObpFormatted":".000","OBP":0,"OpsFormatted":".000","OPS":0},{"PlayerDisplay":"Player, U","PlayerName":"U. Player","Player":{"Position":{"IsPitcher":false,"PositionNumber":2,"PositionString":"C","LongPositionString":"Catcher","PositionText":"catcher","DisplayString":"C"},"Id":0,"Number":17,"DisplayNumber":"17","FirstName":"Unknown","LastName":"Player","DisplayName":"Player #17"},"G":0,"Doubles":0,"Triples":0,"HR":0,"AB":2,"Runs":0,"H":0,"BB":0,"K":1,"SB":0,"CS":0,"RBI":0,"HBP":0,"SAC":0,"SF":0,"BaFormatted":".000","BA":0,"SlgFormatted":".000","SLG":0,"ObpFormatted":".000","OBP":0,"OpsFormatted":".000","OPS":0},{"PlayerDisplay":"Player, U","PlayerName":"U. Player","Player":{"Position":{"IsPitcher":false,"PositionNumber":8,"PositionString":"CF","LongPositionString":"Center Field","PositionText":"center","DisplayString":"CF"},"Id":0,"Number":24,"DisplayNumber":"24","FirstName":"Unknown","LastName":"Player","DisplayName":"Player #24"},"G":0,"Doubles":0,"Triples":0,"HR":0,"AB":2,"Runs":0,"H":0,"BB":0,"K":1,"SB":0,"CS":0,"RBI":0,"HBP":0,"SAC":0,"SF":0,"BaFormatted":".000","BA":0,"SlgFormatted":".000","SLG":0,"ObpFormatted":".000","OBP":0,"OpsFormatted":".000","OPS":0},{"PlayerDisplay":"Player, U","PlayerName":"U. Player","Player":{"Position":{"IsPitcher":true,"PositionNumber":1,"PositionString":"P","LongPositionString":"Pitcher","PositionText":"pitcher","DisplayString":"P"},"Id":0,"Number":3,"DisplayNumber":"3","FirstName":"Unknown","LastName":"Player","DisplayName":"Player #3"},"G":0,"Doubles":0,"Triples":0,"HR":0,"AB":1,"Runs":0,"H":0,"BB":0,"K":0,"SB":0,"CS":0,"RBI":0,"HBP":1,"SAC":0,"SF":0,"BaFormatted":".000","BA":0,"SlgFormatted":".000","SLG":0,"ObpFormatted":".500","OBP":0.5,"OpsFormatted":".500","OPS":0.5},{"PlayerDisplay":"Player, U","PlayerName":"U. Player","Player":{"Position":{"IsPitcher":false,"PositionNumber":9,"PositionString":"RF","LongPositionString":"Right Field","PositionText":"right","DisplayString":"RF"},"Id":0,"Number":11,"DisplayNumber":"11","FirstName":"Unknown","LastName":"Player","DisplayName":"Player #11"},"G":0,"Doubles":0,"Triples":0,"HR":0,"AB":1,"Runs":0,"H":0,"BB":0,"K":0,"SB":0,"CS":0,"RBI":0,"HBP":0,"SAC":0,"SF":0,"BaFormatted":".000","BA":0,"SlgFormatted":".000","SLG":0,"ObpFormatted":".000","OBP":0,"OpsFormatted":".000","OPS":0}],"HomeTeamHitting":[{"PlayerDisplay":"White, M","PlayerName":"M. White","Player":{"Position":{"IsPitcher":true,"PositionNumber":10,"PositionString":"EH","LongPositionString":"Extra Hitter","PositionText":"","DisplayString":"DH / P / C / _1B / IF / OF / EH"},"Id":0,"Number":4,"DisplayNumber":"4","FirstName":"Marchus","LastName":"White","DisplayName":"White"},"G":0,"Doubles":0,"Triples":0,"HR":0,"AB":2,"Runs":1,"H":1,"BB":1,"K":0,"SB":0,"CS":0,"RBI":3,"HBP":0,"SAC":0,"SF":0,"BaFormatted":".500","BA":0.5,"SlgFormatted":".500","SLG":0.5,"ObpFormatted":".667","OBP":0.667,"OpsFormatted":"1.167","OPS":1.167},{"PlayerDisplay":"Millner, J","PlayerName":"J. Millner","Player":{"Position":{"IsPitcher":false,"PositionNumber":5,"PositionString":"3B","LongPositionString":"Third Base","PositionText":"third","DisplayString":"_3B"},"Id":0,"Number":24,"DisplayNumber":"24","FirstName":"Justin","LastName":"Millner","DisplayName":"Millner"},"G":0,"Doubles":0,"Triples":0,"HR":0,"AB":3,"Runs":0,"H":2,"BB":0,"K":0,"SB":0,"CS":0,"RBI":1,"HBP":0,"SAC":0,"SF":0,"BaFormatted":".667","BA":0.667,"SlgFormatted":".667","SLG":0.667,"ObpFormatted":".667","OBP":0.667,"OpsFormatted":"1.334","OPS":1.334},{"PlayerDisplay":"Van Kooten, T","PlayerName":"T. Van Kooten","Player":{"Position":{"IsPitcher":false,"PositionNumber":6,"PositionString":"SS","LongPositionString":"Shortstop","PositionText":"shortstop","DisplayString":"SS"},"Id":0,"Number":27,"DisplayNumber":"27","FirstName":"Tom","LastName":"Van Kooten","DisplayName":"Van Kooten"},"G":0,"Doubles":0,"Triples":0,"HR":0,"AB":2,"Runs":1,"H":1,"BB":1,"K":0,"SB":2,"CS":0,"RBI":1,"HBP":0,"SAC":0,"SF":0,"BaFormatted":".500","BA":0.5,"SlgFormatted":".500","SLG":0.5,"ObpFormatted":".667","OBP":0.667,"OpsFormatted":"1.167","OPS":1.167},{"PlayerDisplay":"Eiden, T","PlayerName":"T. Eiden","Player":{"Position":{"IsPitcher":true,"PositionNumber":10,"PositionString":"EH","LongPositionString":"Extra Hitter","PositionText":"","DisplayString":"DH / P / C / _1B / IF / OF / EH"},"Id":0,"Number":23,"DisplayNumber":"23","FirstName":"Tim","LastName":"Eiden","DisplayName":"Eiden"},"G":0,"Doubles":0,"Triples":0,"HR":0,"AB":2,"Runs":0,"H":0,"BB":0,"K":0,"SB":0,"CS":0,"RBI":1,"HBP":1,"SAC":0,"SF":0,"BaFormatted":".000","BA":0,"SlgFormatted":".000","SLG":0,"ObpFormatted":".333","OBP":0.333,"OpsFormatted":".333","OPS":0.333},{"PlayerDisplay":"Deere, J","PlayerName":"J. Deere","Player":{"Position":{"IsPitcher":false,"PositionNumber":5,"PositionString":"3B","LongPositionString":"Third Base","PositionText":"third","DisplayString":"_3B"},"Id":0,"Number":2,"DisplayNumber":"2","FirstName":"James","LastName":"Deere","DisplayName":"Deere"},"G":0,"Doubles":0,"Triples":0,"HR":0,"AB":1,"Runs":0,"H":0,"BB":1,"K":0,"SB":0,"CS":0,"RBI":0,"HBP":0,"SAC":0,"SF":0,"BaFormatted":".000","BA":0,"SlgFormatted":".000","SLG":0,"ObpFormatted":".500","OBP":0.5,"OpsFormatted":".500","OPS":0.5},{"PlayerDisplay":"Johnson, F","PlayerName":"F. Johnson","Player":{"Position":{"IsPitcher":false,"PositionNumber":2,"PositionString":"C","LongPositionString":"Catcher","PositionText":"catcher","DisplayString":"C"},"Id":0,"Number":8,"DisplayNumber":"8","FirstName":"Francisco","LastName":"Johnson","DisplayName":"Johnson"},"G":0,"Doubles":0,"Triples":0,"HR":0,"AB":2,"Runs":1,"H":0,"BB":0,"K":0,"SB":0,"CS":0,"RBI":0,"HBP":0,"SAC":0,"SF":0,"BaFormatted":".000","BA":0,"SlgFormatted":".000","SLG":0,"ObpFormatted":".000","OBP":0,"OpsFormatted":".000","OPS":0},{"PlayerDisplay":"Vasquez, M","PlayerName":"M. Vasquez","Player":{"Position":{"IsPitcher":false,"PositionNumber":3,"PositionString":"1B","LongPositionString":"First Base","PositionText":"first","DisplayString":"_1B"},"Id":0,"Number":18,"DisplayNumber":"18","FirstName":"Mike","LastName":"Vasquez","DisplayName":"Vasquez"},"G":0,"Doubles":1,"Triples":0,"HR":0,"AB":3,"Runs":3,"H":3,"BB":0,"K":0,"SB":0,"CS":0,"RBI":1,"HBP":0,"SAC":0,"SF":0,"BaFormatted":"1.000","BA":1,"SlgFormatted":"1.333","SLG":1.333,"ObpFormatted":"1.000","OBP":1,"OpsFormatted":"2.333","OPS":2.333},{"PlayerDisplay":"Mozo, V","PlayerName":"V. Mozo","Player":{"Position":{"IsPitcher":false,"PositionNumber":9,"PositionString":"RF","LongPositionString":"Right Field","PositionText":"right","DisplayString":"RF"},"Id":0,"Number":69,"DisplayNumber":"69","FirstName":"Victor","LastName":"Mozo","DisplayName":"Mozo"},"G":0,"Doubles":0,"Triples":0,"HR":0,"AB":0,"Runs":1,"H":0,"BB":2,"K":0,"SB":0,"CS":0,"RBI":0,"HBP":0,"SAC":0,"SF":0,"BaFormatted":".000","BA":null,"SlgFormatted":".000","SLG":null,"ObpFormatted":"1.000","OBP":1,"OpsFormatted":"1.000","OPS":1},{"PlayerDisplay":"DeSoto, I","PlayerName":"I. DeSoto","Player":{"Position":{"IsPitcher":false,"PositionNumber":8,"PositionString":"CF","LongPositionString":"Center Field","PositionText":"center","DisplayString":"CF"},"Id":0,"Number":9,"DisplayNumber":"9","FirstName":"Ian","LastName":"DeSoto","DisplayName":"DeSoto"},"G":0,"Doubles":0,"Triples":0,"HR":0,"AB":1,"Runs":3,"H":0,"BB":1,"K":0,"SB":1,"CS":0,"RBI":0,"HBP":1,"SAC":0,"SF":0,"BaFormatted":".000","BA":0,"SlgFormatted":".000","SLG":0,"ObpFormatted":".667","OBP":0.667,"OpsFormatted":".667","OPS":0.667},{"PlayerDisplay":"Flores, D","PlayerName":"D. Flores","Player":{"Position":{"IsPitcher":false,"PositionNumber":4,"PositionString":"2B","LongPositionString":"Second Base","PositionText":"second","DisplayString":"_2B"},"Id":0,"Number":20,"DisplayNumber":"20","FirstName":"Dave","LastName":"Flores","DisplayName":"Flores"},"G":0,"Doubles":0,"Triples":0,"HR":0,"AB":2,"Runs":1,"H":1,"BB":1,"K":0,"SB":0,"CS":0,"RBI":0,"HBP":0,"SAC":0,"SF":0,"BaFormatted":".500","BA":0.5,"SlgFormatted":".500","SLG":0.5,"ObpFormatted":".667","OBP":0.667,"OpsFormatted":"1.167","OPS":1.167},{"PlayerDisplay":"Tandon, D","PlayerName":"D. Tandon","Player":{"Position":{"IsPitcher":false,"PositionNumber":8,"PositionString":"CF","LongPositionString":"Center Field","PositionText":"center","DisplayString":"CF"},"Id":0,"Number":25,"DisplayNumber":"25","FirstName":"Darius","LastName":"Tandon","DisplayName":"Tandon"},"G":0,"Doubles":0,"Triples":0,"HR":0,"AB":0,"Runs":1,"H":0,"BB":2,"K":0,"SB":0,"CS":0,"RBI":1,"HBP":0,"SAC":0,"SF":0,"BaFormatted":".000","BA":null,"SlgFormatted":".000","SLG":null,"ObpFormatted":"1.000","OBP":1,"OpsFormatted":"1.000","OPS":1},{"PlayerDisplay":"Russman, E","PlayerName":"E. Russman","Player":{"Position":{"IsPitcher":false,"PositionNumber":7,"PositionString":"LF","LongPositionString":"Left Field","PositionText":"left","DisplayString":"LF"},"Id":0,"Number":44,"DisplayNumber":"44","FirstName":"Eric","LastName":"Russman","DisplayName":"Russman"},"G":0,"Doubles":0,"Triples":0,"HR":0,"AB":1,"Runs":0,"H":0,"BB":0,"K":1,"SB":0,"CS":0,"RBI":0,"HBP":0,"SAC":0,"SF":0,"BaFormatted":".000","BA":0,"SlgFormatted":".000","SLG":0,"ObpFormatted":".000","OBP":0,"OpsFormatted":".000","OPS":0},{"PlayerDisplay":"Simon, T","PlayerName":"T. Simon","Player":{"Position":{"IsPitcher":false,"PositionNumber":2,"PositionString":"C","LongPositionString":"Catcher","PositionText":"catcher","DisplayString":"C"},"Id":0,"Number":5,"DisplayNumber":"5","FirstName":"Tom","LastName":"Simon","DisplayName":"Simon"},"G":0,"Doubles":0,"Triples":0,"HR":0,"AB":1,"Runs":0,"H":0,"BB":0,"K":0,"SB":0,"CS":0,"RBI":0,"HBP":0,"SAC":0,"SF":0,"BaFormatted":".000","BA":0,"SlgFormatted":".000","SLG":0,"ObpFormatted":".000","OBP":0,"OpsFormatted":".000","OPS":0},{"PlayerDisplay":"Zakem, J","PlayerName":"J. Zakem","Player":{"Position":{"IsPitcher":false,"PositionNumber":9,"PositionString":"RF","LongPositionString":"Right Field","PositionText":"right","DisplayString":"RF"},"Id":0,"Number":88,"DisplayNumber":"88","FirstName":"Jeff","LastName":"Zakem","DisplayName":"Zakem"},"G":0,"Doubles":0,"Triples":0,"HR":0,"AB":1,"Runs":0,"H":0,"BB":0,"K":0,"SB":0,"CS":0,"RBI":0,"HBP":0,"SAC":0,"SF":0,"BaFormatted":".000","BA":0,"SlgFormatted":".000","SLG":0,"ObpFormatted":".000","OBP":0,"OpsFormatted":".000","OPS":0},{"PlayerDisplay":"McElhaney, B","PlayerName":"B. McElhaney","Player":{"Position":{"IsPitcher":true,"PositionNumber":1,"PositionString":"P","LongPositionString":"Pitcher","PositionText":"pitcher","DisplayString":"P"},"Id":0,"Number":12,"DisplayNumber":"12","FirstName":"Brendan","LastName":"McElhaney","DisplayName":"McElhaney"},"G":0,"Doubles":1,"Triples":0,"HR":0,"AB":1,"Runs":0,"H":1,"BB":0,"K":0,"SB":0,"CS":0,"RBI":2,"HBP":0,"SAC":0,"SF":0,"BaFormatted":"1.000","BA":1,"SlgFormatted":"2.000","SLG":2,"ObpFormatted":"1.000","OBP":1,"OpsFormatted":"3.000","OPS":3}],"AwayTeamPitching":[{"PitcherDisplay":"U. Player (L)","PlayerName":"U. Player","Player":{"Position":{"IsPitcher":true,"PositionNumber":1,"PositionString":"P","LongPositionString":"Pitcher","PositionText":"pitcher","DisplayString":"P"},"Id":0,"Number":3,"DisplayNumber":"3","FirstName":"Unknown","LastName":"Player","DisplayName":"Player"},"Decision":2,"DecisionDiplay":"L","GS":1,"H":5,"HR":0,"BB":5,"K":0,"HB":0,"BF":20,"R":6,"ER":3,"Outs":11,"IP":"3.2","CG":0,"EraFormatted":"5.73","ERA":5.73,"WhipFormatted":"2.73","WHIP":2.73,"K9":0,"BB9":9.55,"Pitches":71,"Balls":34,"Strikes":37,"GroundOuts":3,"FlyOuts":6},{"PitcherDisplay":"U. Player ","PlayerName":"U. Player","Player":{"Position":{"IsPitcher":true,"PositionNumber":1,"PositionString":"P","LongPositionString":"Pitcher","PositionText":"pitcher","DisplayString":"P"},"Id":0,"Number":7,"DisplayNumber":"7","FirstName":"Unknown","LastName":"Player","DisplayName":"Player"},"Decision":0,"DecisionDiplay":"","GS":0,"H":1,"HR":0,"BB":4,"K":0,"HB":0,"BF":5,"R":4,"ER":3,"Outs":0,"IP":"0.0","CG":0,"EraFormatted":".00","ERA":null,"WhipFormatted":".00","WHIP":null,"K9":null,"BB9":null,"Pitches":24,"Balls":18,"Strikes":6,"GroundOuts":0,"FlyOuts":0},{"PitcherDisplay":"U. Player ","PlayerName":"U. Player","Player":{"Position":{"IsPitcher":true,"PositionNumber":1,"PositionString":"P","LongPositionString":"Pitcher","PositionText":"pitcher","DisplayString":"P"},"Id":0,"Number":99,"DisplayNumber":"99","FirstName":"Unknown","LastName":"Player","DisplayName":"Player"},"Decision":0,"DecisionDiplay":"","GS":0,"H":3,"HR":0,"BB":0,"K":1,"HB":2,"BF":9,"R":2,"ER":2,"Outs":3,"IP":"1.0","CG":0,"EraFormatted":"14.00","ERA":14,"WhipFormatted":"3.00","WHIP":3,"K9":7,"BB9":0,"Pitches":30,"Balls":14,"Strikes":16,"GroundOuts":1,"FlyOuts":1}],"HomeTeamPitching":[{"PitcherDisplay":"T. Van Kooten (W)","PlayerName":"T. Van Kooten","Player":{"Position":{"IsPitcher":true,"PositionNumber":1,"PositionString":"P","LongPositionString":"Pitcher","PositionText":"pitcher","DisplayString":"P"},"Id":0,"Number":27,"DisplayNumber":"27","FirstName":"Tom","LastName":"Van Kooten","DisplayName":"Van Kooten"},"Decision":1,"DecisionDiplay":"W","GS":1,"H":1,"HR":0,"BB":0,"K":4,"HB":1,"BF":14,"R":0,"ER":0,"Outs":12,"IP":"4.0","CG":0,"EraFormatted":".00","ERA":0,"WhipFormatted":".25","WHIP":0.25,"K9":7,"BB9":0,"Pitches":54,"Balls":14,"Strikes":40,"GroundOuts":4,"FlyOuts":4},{"PitcherDisplay":"B. McElhaney ","PlayerName":"B. McElhaney","Player":{"Position":{"IsPitcher":true,"PositionNumber":1,"PositionString":"P","LongPositionString":"Pitcher","PositionText":"pitcher","DisplayString":"P"},"Id":0,"Number":12,"DisplayNumber":"12","FirstName":"Brendan","LastName":"McElhaney","DisplayName":"McElhaney"},"Decision":0,"DecisionDiplay":"","GS":0,"H":0,"HR":0,"BB":0,"K":1,"HB":0,"BF":3,"R":0,"ER":0,"Outs":3,"IP":"1.0","CG":0,"EraFormatted":".00","ERA":0,"WhipFormatted":".00","WHIP":0,"K9":7,"BB9":0,"Pitches":11,"Balls":2,"Strikes":9,"GroundOuts":1,"FlyOuts":1}],"WinningPitcher":{"Position":null,"Id":0,"Number":27,"DisplayNumber":"27","FirstName":"Tom","LastName":"Van Kooten","DisplayName":"Van Kooten"},"LosingPitcher":{"Position":null,"Id":0,"Number":3,"DisplayNumber":"3","FirstName":"Unknown","LastName":"Player","DisplayName":"Player"},"current_ab":{"balls":1,"strikes":2,"outs":0,"pitches":["Foul.  ","Ball.  ","In play.  "],"inning_number":5,"inning_half":"Bottom","on_first":null,"on_second":"McElhaney","on_third":"Flores"},"defense":{"6":"Player","4":"Player","3":"Player","7":"Player","5":"Player","2":"Player","8":"Player","1":"Player","9":"Player"},"home_score":12,"away_score":0,"home_hits":9,"away_hits":1,"home_errors":0,"away_errors":2,"ScoringPlays":[{"HomeScore":2,"AwayScore":0,"InningNumber":3,"Team":"Electrons","Play":"White singled to right.  Vasquez and DeSoto scored.  "},{"HomeScore":3,"AwayScore":0,"InningNumber":4,"Team":"Electrons","Play":"Johnson reached on an error to shortstop.  Van Kooten scored.  "},{"HomeScore":4,"AwayScore":0,"InningNumber":4,"Team":"Electrons","Play":"Vasquez doubled to left.  Johnson scored.  "},{"HomeScore":5,"AwayScore":0,"InningNumber":4,"Team":"Electrons","Play":"Vasquez scored on error by catcher.  "},{"HomeScore":6,"AwayScore":0,"InningNumber":4,"Team":"Electrons","Play":"Tandon walked.  Mozo scored.  "},{"HomeScore":7,"AwayScore":0,"InningNumber":4,"Team":"Electrons","Play":"White walked.  DeSoto scored.  "},{"HomeScore":8,"AwayScore":0,"InningNumber":4,"Team":"Electrons","Play":"Millner reached on infield single.  Flores scored.  "},{"HomeScore":9,"AwayScore":0,"InningNumber":4,"Team":"Electrons","Play":"Van Kooten walked.  Tandon scored.  "},{"HomeScore":10,"AwayScore":0,"InningNumber":4,"Team":"Electrons","Play":"Eiden hit by pitch.  White scored.  "},{"HomeScore":12,"AwayScore":0,"InningNumber":5,"Team":"Electrons","Play":"McElhaney doubled to center.  Vasquez and DeSoto scored.  "}],"GameSummary":[{"Description":"Top of 1","Summary":"0 Runs, 0 Hits, 0 Errors, 0 Left","Events":[{"EventText":"Foul.  Ball.  Player #0 grounded out to first.  ","ScoringPlay":false},{"EventText":"Ball.  Ball.  Called strike.  Strike swinging.  Foul.  Player #2 flied out to center.  ","ScoringPlay":false},{"EventText":"Called strike.  Called strike.  Strike swinging.  Player #34 struck out swinging.  ","ScoringPlay":false}]},{"Description":"Bottom of 1","Summary":"0 Runs, 1 Hit, 0 Errors, 0 Left","Events":[{"EventText":"Ball.  Called strike.  Ball.  Ball.  Called strike.  White grounded out to second.  ","ScoringPlay":false},{"EventText":"Ball.  Millner singled to right.  ","ScoringPlay":false},{"EventText":"Strike swinging.  Strike swinging.  Van Kooten lined into a double play to third.  Millner out at first.  ","ScoringPlay":false}]},{"Description":"Top of 2","Summary":"0 Runs, 0 Hits, 0 Errors, 0 Left","Events":[{"EventText":"Strike swinging.  Player #7 grounded out to third.  ","ScoringPlay":false},{"EventText":"Foul.  Ball.  Called strike.  Ball.  Ball.  Strike swinging.  Player #99 struck out swinging.  ","ScoringPlay":false},{"EventText":"Strike swinging.  Called strike.  Foul.  Strike swinging.  Player #17 struck out swinging.  ","ScoringPlay":false}]},{"Description":"Bottom of 2","Summary":"0 Runs, 0 Hits, 0 Errors, 0 Left","Events":[{"EventText":"Eiden flied out to shortstop.  ","ScoringPlay":false},{"EventText":"Ball.  Ball.  Ball.  Called strike.  Ball.  Deere walked.  ","ScoringPlay":false},{"EventText":"Foul.  Johnson lined into a double play to third.  Deere out at first.  ","ScoringPlay":false}]},{"Description":"Top of 3","Summary":"0 Runs, 0 Hits, 0 Errors, 1 Left","Events":[{"EventText":"Foul.  Player #24 grounded out to first.  ","ScoringPlay":false},{"EventText":"Foul.  Ball.  Player #3 hit by pitch.  ","ScoringPlay":false},{"EventText":"Called strike.  Ball.  Player #3 to second on wild pitch.  Strike swinging.  Foul.  Player #11 flied out to center.  ","ScoringPlay":false},{"EventText":"Ball.  Player #0 flied out to right.  ","ScoringPlay":false}]},{"Description":"Bottom of 3","Summary":"2 Runs, 2 Hits, 0 Errors, 2 Left","Events":[{"EventText":"Called strike.  Called strike.  Foul.  Vasquez singled to center.  ","ScoringPlay":false},{"EventText":"Ball.  Ball.  Vasquez to second on wild pitch.  Foul.  Ball.  Ball.  Mozo walked.  ","ScoringPlay":false},{"EventText":"Foul.  DeSoto reached on fielder\u0027s choice to shortstop.  Mozo out at second.  ","ScoringPlay":false},{"EventText":"Called strike.  DeSoto stole second.  Foul.  Flores flied out to first.  ","ScoringPlay":false},{"EventText":"Called strike.  Ball.  Ball.  Ball.  Ball.  Tandon walked.  ","ScoringPlay":false},{"EventText":"Ball.  Strike swinging.  Ball.  Ball.  White singled to right.  Vasquez and DeSoto scored.  ","ScoringPlay":true},{"EventText":"Millner flied out to first.  ","ScoringPlay":false}]},{"Description":"Top of 4","Summary":"0 Runs, 1 Hit, 0 Errors, 1 Left","Events":[{"EventText":"Player #2 grounded out to third.  ","ScoringPlay":false},{"EventText":"Ball.  Ball.  Ball.  Called strike.  Called strike.  Foul.  Foul.  Foul.  Player #34 flied out to center.  ","ScoringPlay":false},{"EventText":"Strike swinging.  Strike swinging.  Player singled to center.  ","ScoringPlay":false},{"EventText":"Strike swinging.  Foul.  Ball.  Ball.  Player #7 to second on passed ball.  Foul.  Strike swinging.  Player #99 struck out swinging.  ","ScoringPlay":false}]},{"Description":"Bottom of 4","Summary":"8 Runs, 3 Hits, 2 Errors, 3 Left","Events":[{"EventText":"Called strike.  Ball.  Van Kooten reached on infield single.  ","ScoringPlay":false},{"EventText":"Ball.  Van Kooten stole second.  Foul.  Ball.  Ball.  Eiden grounded out to shortstop.  ","ScoringPlay":false},{"EventText":"Ball.  Ball.  Strike swinging.  Deere flied out to center.  ","ScoringPlay":false},{"EventText":"Called strike.  Van Kooten stole third.  Ball.  Foul.  Johnson reached on an error to shortstop.  Van Kooten scored.  ","ScoringPlay":true},{"EventText":"Vasquez doubled to left.  Johnson scored.  ","ScoringPlay":true},{"EventText":"Ball.  Ball.  Ball.  Ball.  Mozo walked.  ","ScoringPlay":false},{"EventText":"Vasquez to third, Mozo to second on wild pitch.  Vasquez scored on error by catcher.  Ball.  Player #7 relieved Player #3.  Ball.  Ball.  Ball.  DeSoto walked.  ","ScoringPlay":true},{"EventText":"Ball.  Ball.  Called strike.  Ball.  Called strike.  Ball.  Flores walked.  ","ScoringPlay":false},{"EventText":"Ball.  Called strike.  Ball.  Ball.  Ball.  Tandon walked.  Mozo scored.  ","ScoringPlay":true},{"EventText":"Ball.  Called strike.  Ball.  Ball.  Ball.  White walked.  DeSoto scored.  ","ScoringPlay":true},{"EventText":"Called strike.  Ball.  Ball.  Millner reached on infield single.  Flores scored.  ","ScoringPlay":true},{"EventText":"Ball.  Ball.  Ball.  Foul.  Foul.  Ball.  Van Kooten walked.  Tandon scored.  ","ScoringPlay":true},{"EventText":"Player #99 relieved Player #7.  Ball.  Ball.  Ball.  Eiden hit by pitch.  White scored.  ","ScoringPlay":true},{"EventText":"Russman batted for Deere.  ","ScoringPlay":false},{"EventText":"Strike swinging.  Ball.  Ball.  Called strike.  Strike swinging.  Russman struck out swinging.  ","ScoringPlay":false}]},{"Description":"Top of 5","Summary":"0 Runs, 0 Hits, 0 Errors, 0 Left","Events":[{"EventText":"B. McElhaney relieved T. Van Kooten.  McElhaney entered the game for Tandon.  Zakem entered the game for Mozo.  Simon entered the game for Johnson.  Called strike.  Ball.  Foul.  Player #17 flied out to center.  ","ScoringPlay":false},{"EventText":"Called strike.  Strike swinging.  Strike swinging.  Player #24 struck out swinging.  ","ScoringPlay":false},{"EventText":"Foul.  Called strike.  Ball.  Player #3 grounded out to shortstop.  ","ScoringPlay":false}]},{"Description":"Bottom of 5","Summary":"2 Runs, 3 Hits, 0 Errors, 0 Left","Events":[{"EventText":"Ball.  Ball.  Strike swinging.  Ball.  Simon grounded out to second.  ","ScoringPlay":false},{"EventText":"Ball.  Called strike.  Called strike.  Ball.  Vasquez singled to left.  ","ScoringPlay":false},{"EventText":"Ball.  Foul.  Zakem flied out to shortstop.  ","ScoringPlay":false},{"EventText":"Called strike.  Ball.  Called strike.  Ball.  DeSoto hit by pitch.  ","ScoringPlay":false},{"EventText":"Called strike.  Flores singled to left.  ","ScoringPlay":false},{"EventText":"Foul.  Ball.  McElhaney doubled to center.  Vasquez and DeSoto scored.  ","ScoringPlay":true}]}],"GameLineScore":{"HomeLine":{"Name":"Electrons","InningLines":[{"Runs":2,"Hits":3,"Errors":0,"Number":5},{"Runs":8,"Hits":3,"Errors":2,"Number":4},{"Runs":2,"Hits":2,"Errors":0,"Number":3},{"Runs":0,"Hits":0,"Errors":0,"Number":2},{"Runs":0,"Hits":1,"Errors":0,"Number":1}]},"AwayLine":{"Name":"Blazers","InningLines":[{"Runs":0,"Hits":0,"Errors":0,"Number":5},{"Runs":0,"Hits":1,"Errors":0,"Number":4},{"Runs":0,"Hits":0,"Errors":0,"Number":3},{"Runs":0,"Hits":0,"Errors":0,"Number":2},{"Runs":0,"Hits":0,"Errors":0,"Number":1}]}},"home_risp":{"abs":12,"hits":5},"away_risp":{"abs":3,"hits":0}}